plugin_megaexample/__init__.py
plugin_megaexample/urls.py
plugin_megaexample/views.py
plugin_megaexample/templates/upload.html
plugin_megaexample/xlsx_parser_lib/__init__.py
plugin_megaexample/xlsx_parser_lib/exceptions.py
plugin_megaexample/xlsx_parser_lib/xlsx_parser.py
plugin_megaexample-0.0.2.dist-info/METADATA
plugin_megaexample-0.0.2.dist-info/WHEEL
plugin_megaexample-0.0.2.dist-info/entry_points.txt
plugin_megaexample-0.0.2.dist-info/top_level.txt
plugin_megaexample-0.0.2.dist-info/RECORD
