Metadata-Version: 2.4
Name: plugin-megaexample
Version: 0.0.2
Summary: Plugin MegaExample
Author-email: Ivan Dorodnitsyn <ivdorodnitsyn@gmail.com>
Project-URL: Homepage, https://github.com/evildarius/plugin-megaexample
Classifier: Programming Language :: Python :: 3
Classifier: License :: OSI Approved :: MIT License
Classifier: Operating System :: OS Independent
Requires-Python: >=3.11
Requires-Dist: requests>=2.28.0
Requires-Dist: openpyxl==3.1.1
